README.txt
setup.py
Products/__init__.py
Products.Zope_Hotfix_CVE_2010_1104.egg-info/PKG-INFO
Products.Zope_Hotfix_CVE_2010_1104.egg-info/SOURCES.txt
Products.Zope_Hotfix_CVE_2010_1104.egg-info/dependency_links.txt
Products.Zope_Hotfix_CVE_2010_1104.egg-info/namespace_packages.txt
Products.Zope_Hotfix_CVE_2010_1104.egg-info/not-zip-safe
Products.Zope_Hotfix_CVE_2010_1104.egg-info/requires.txt
Products.Zope_Hotfix_CVE_2010_1104.egg-info/top_level.txt
Products/Zope_Hotfix_CVE_2010_1104/__init__.py